gaio/__init__.py
gaio/asyncsocket.py
gaio/eventloop.py
gaio/file.py
gaio/promise.py
gaio/reactors.py
ugaioni-0.1.0.dist-info/LICENSE
ugaioni-0.1.0.dist-info/METADATA
ugaioni-0.1.0.dist-info/WHEEL
ugaioni-0.1.0.dist-info/top_level.txt
ugaioni-0.1.0.dist-info/RECORD
