Metadata-Version: 2.1
Name: ugaioni
Version: 0.1.0
Summary: gaio is a high-performance asynchronous I/O library for scheduling coroutine-based operations in Python, featuring a robust event loop and seamless integration with existing applications.
Home-page: https://github.com/iadityanath8/gaio
Author: Aditya Nath Goswami
Author-email: your.email@example.com
License: GPLv3
Classifier: Programming Language :: Python :: 3
Classifier: License :: OSI Approved :: GNU General Public License v3 (GPLv3)
Classifier: Operating System :: OS Independent
License-File: LICENSE
